db_migrator-1.0.2.dist-info/DESCRIPTION.rst
db_migrator-1.0.2.dist-info/METADATA
db_migrator-1.0.2.dist-info/RECORD
db_migrator-1.0.2.dist-info/WHEEL
db_migrator-1.0.2.dist-info/entry_points.txt
db_migrator-1.0.2.dist-info/metadata.json
db_migrator-1.0.2.dist-info/top_level.txt
dbmigrator/__init__.py
dbmigrator/cli.py
dbmigrator/utils.py
dbmigrator/commands/__init__.py
dbmigrator/commands/generate.py
dbmigrator/commands/init.py
dbmigrator/commands/list.py
dbmigrator/commands/mark.py
dbmigrator/commands/migrate.py
dbmigrator/commands/rollback.py
dbmigrator/tests/__init__.py
dbmigrator/tests/test_cli.py
dbmigrator/tests/test_utils.py
dbmigrator/tests/testing.py
