Metadata-Version: 2.0
Name: db-migrator
Version: 1.0.2
Summary: Python package to migrate postgresql database
Home-page: https://github.com/karenc/db-migrator
Author: Connexions
Author-email: info@cnx.org
License: AGPL, see also LICENSE.txt
Platform: UNKNOWN
Requires-Dist: psycopg2 (>=2.7)
